janim_stdio_i/__init__.py
janim_stdio_i/__main__.py
janim_stdio_i/cli.py
janim_stdio_i/listener.py
janim_stdio_i/logger.py
janim_stdio_i/viewer.py
janim_stdio_i/locale/__init__.py
janim_stdio_i/locale/i18n.py
janim_stdio_i/locale/zh_CN/LC_MESSAGES/__main__.mo
janim_stdio_i/locale/zh_CN/LC_MESSAGES/cli.mo
janim_stdio_i/locale/zh_CN/LC_MESSAGES/listener.mo
janim_stdio_interact-0.1.3.dist-info/entry_points.txt
janim_stdio_interact-0.1.3.dist-info/licenses/LICENSE
janim_stdio_interact-0.1.3.dist-info/WHEEL
janim_stdio_interact-0.1.3.dist-info/METADATA
janim_stdio_interact-0.1.3.dist-info/RECORD
