Metadata-Version: 2.4
Name: janim-stdio-interact
Version: 0.1.3
Summary: A utility library for interacting with JAnim GUI via standard input/output
Author-email: jkjkil4 <1173374788@qq.com>
Requires-Python: >=3.12
License-File: LICENSE
Requires-Dist: janim[gui]>=4.0.0a5
Project-URL: Source, https://github.com/jkjkil4/janim-stdio-interact
